T04SOP/t04sop.v
module t04sop();

  wire out0,out1,out2,out3,out4,out5,out6,out7,out8,out9,out10,out11;
  reg A,B,C,D;

  not G1(out1,A);
  not G2(out2,B);
  not G3(out3,C);
  not G4(out4,D);
  and G5(out5,out1,out2,out3,out4);
  and G6(out6,out1,out2,C,out4);
  and G7(out7,out1,out2,C,D);
  and G8(out8,out1,B,C,out4);
  and G9(out9,out1,B,C,D);
  and G10(out10,A,out2,out3,out4);
  and G11(out11,A,out2,C,out4);
  or  G0(out0,out5,out6,out7,out8,out9,out10,out11);

  initial begin
    $display("A B C D | Y");
    $display("--------|--");
    $monitor("%b %b %b %b | %b", A, B, C, D, out0);
    A = 0; B = 0; C = 0; D = 0;
    #1 D = 1;
    #1 C = 1; D = 0;
    #1 C = 1; D = 1;
    #1 B = 1; C = 0; D = 0;
    #1 B = 1; C = 0; D = 1;
    #1 B = 1; C = 1; D = 0;
    #1 B = 1; C = 1; D = 1;
    #1 A = 1; B = 0; C = 0; D = 0;
    #1 A = 1; B = 0; C = 0; D = 1;
    #1 A = 1; B = 0; C = 1; D = 0;
    #1 A = 1; B = 0; C = 1; D = 1;
    #1 A = 1; B = 1; C = 0; D = 0;
    #1 A = 1; B = 1; C = 0; D = 1;
    #1 A = 1; B = 1; C = 1; D = 0;
    #1 A = 1; B = 1; C = 1; D = 1;
    #1 $finish;
  end

  initial begin
    $dumpfile("t04sop_tb.vcd");
    $dumpvars(0, t04sop);
  end
endmodule

T04SOP/t04sop_tb.vcd
$date
	Sat Aug 01 22:35:42 2020
$end
$version
	Icarus Verilog
$end
$timescale
	1ps
$end
$scope module t04sop $end
$var wire 1 ! out0 $end
$var wire 1 " out1 $end
$var wire 1 # out10 $end
$var wire 1 $ out11 $end
$var wire 1 % out2 $end
$var wire 1 & out3 $end
$var wire 1 ' out4 $end
$var wire 1 ( out5 $end
$var wire 1 ) out6 $end
$var wire 1 * out7 $end
$var wire 1 + out8 $end
$var wire 1 , out9 $end
$var reg 1 - A $end
$var reg 1 . B $end
$var reg 1 / C $end
$var reg 1 0 D $end
$upscope $end
$enddefinitions $end
#0
$dumpvars
00
0/
0.
0-
0,
0+
0*
0)
1(
1'
1&
1%
0$
0#
1"
1!
$end
#1
0!
0(
0'
10
#2
1!
1)
1'
0&
00
1/
#3
0)
1*
0'
10
#4
0!
1'
0*
1&
0%
00
0/
1.
#5
0'
10
#6
1!
1+
1'
0&
00
1/
#7
0+
1,
0'
10
#8
1#
1'
1&
0,
1%
0"
00
0/
0.
1-
#9
0!
0#
0'
10
#10
1!
1$
1'
0&
00
1/
#11
0!
0$
0'
10
#12
1'
1&
0%
00
0/
1.
#13
0'
10
#14
1'
0&
00
1/
#15
0'
10
