T01POS/t01pos.v
module t01pos();

  wire out0,out1,out2,out3,out4,out5,out6;
  reg A,B,C,D;

  not G4(out4,A);
  not G5(out5,B);
  not G6(out6,C);
  or  G1(out1,A,B,out6);
  or  G2(out2,A,out5,out6);
  or  G3(out3,out4,out5,C);
  and G0(out0,out1,out2,out3);

  initial begin
    $display("A B C | Y");
    $display("------|--");
    $monitor("%b %b %b | %b", A, B, C, out0);
    A = 0; B = 0; C = 0;
    #1 C = 1;
    #1 B = 1; C = 0;
    #1 B = 1; C = 1;
    #1 A = 1; B = 0; C = 0;
    #1 A = 1; B = 0; C = 1;
    #1 A = 1; B = 1; C = 0;
    #1 A = 1; B = 1; C = 1;
    #1 $finish;
  end

  initial begin 
    $dumpfile("t01pos_tb.vcd");
    $dumpvars(0, t01pos);
  end
endmodule

T01POS/t01pos_tb.vcd
$date
	Sat Aug 01 19:19:46 2020
$end
$version
	Icarus Verilog
$end
$timescale
	1ps
$end
$scope module t01pos $end
$var wire 1 ! out0 $end
$var wire 1 " out1 $end
$var wire 1 # out2 $end
$var wire 1 $ out3 $end
$var wire 1 % out4 $end
$var wire 1 & out5 $end
$var wire 1 ' out6 $end
$var reg 1 ( A $end
$var reg 1 ) B $end
$var reg 1 * C $end
$upscope $end
$enddefinitions $end
#0
$dumpvars
0*
0)
0(
1'
1&
1%
1$
1#
1"
1!
$end
#1
0!
0"
0'
1*
#2
1!
1'
1"
0&
0*
1)
#3
0!
0#
0'
1*
#4
1!
1'
1&
1#
0%
0*
0)
1(
#5
0'
1*
#6
0!
0$
1'
0&
0*
1)
#7
1!
1$
0'
1*
